<?xml version="1.0" encoding="UTF-8" standalone="yes"?>
<trpDocMetadata>
    <docId>1687897</docId>
    <title>Dagboek Els Polak, deel 1</title>
    <uploadTimestamp>1701476445265</uploadTimestamp>
    <uploader>j.aerts@uva.nl</uploader>
    <uploaderId>145668</uploaderId>
    <nrOfPages>35</nrOfPages>
    <pageId>61988530</pageId>
    <url>https://files.transkribus.eu/Get?fileType=view&amp;id=KPWKPXUCTNCYPEHCDRJJEVDF</url>
    <thumbUrl>https://files.transkribus.eu/Get?fileType=thumb&amp;id=KPWKPXUCTNCYPEHCDRJJEVDF</thumbUrl>
    <status>0</status>
    <fimgStoreColl>TrpDoc_DEA_1687897</fimgStoreColl>
    <origDocId>0</origDocId>
    <collectionList>
        <colList>
            <colId>221243</colId>
            <colName>ATM Amsterdam Diaries</colName>
            <description>created by j.aerts@uva.nl</description>
            <crowdsourcing>false</crowdsourcing>
            <elearning>false</elearning>
            <nrOfDocuments>0</nrOfDocuments>
        </colList>
    </collectionList>
    <mainColId>221243</mainColId>
</trpDocMetadata>
